[1,["e73/nRWMBKrIjyssLGhXgd@6c48a"],["_textureSource"],["cc.SpriteFrame"],0,[{"name":"4_e7dff9d1","rect":{"x":20,"y":20,"width":92,"height":54},"offset":{"x":0,"y":-0.5},"originalSize":{"width":132,"height":93},"rotated":false,"capInsets":[0,0,0,0],"vertices":{"rawPosition":[-46,-27,0,46,-27,0,-46,27,0,46,27,0],"indexes":[0,1,2,2,1,3],"uv":[20,73,112,73,20,19,112,19],"nuv":[0.15151515151515152,0.20430107526881722,0.8484848484848485,0.20430107526881722,0.15151515151515152,0.7849462365591398,0.8484848484848485,0.7849462365591398],"minPos":{"x":-46,"y":-27,"z":0},"maxPos":{"x":46,"y":27,"z":0}},"packable":true,"pixelsToUnit":100,"pivot":{"x":0.5,"y":0.5},"meshType":0}],[0],0,[0],[0],[0]]
